.gitignore
.travis.yml
LICENSE
README.md
setup.py
Orange3_Ancient_Greek_Metrics.egg-info/PKG-INFO
Orange3_Ancient_Greek_Metrics.egg-info/SOURCES.txt
Orange3_Ancient_Greek_Metrics.egg-info/dependency_links.txt
Orange3_Ancient_Greek_Metrics.egg-info/entry_points.txt
Orange3_Ancient_Greek_Metrics.egg-info/namespace_packages.txt
Orange3_Ancient_Greek_Metrics.egg-info/not-zip-safe
Orange3_Ancient_Greek_Metrics.egg-info/requires.txt
Orange3_Ancient_Greek_Metrics.egg-info/top_level.txt
doc/Makefile
doc/conf.py
doc/index.rst
doc/make.bat
doc/widgets/mywidget.md
doc/widgets/icons/mywidget.png
orangecontrib/__init__.py
orangecontrib/ancient_greek_metrics/__init__.py
orangecontrib/ancient_greek_metrics/tests/__init__.py
orangecontrib/ancient_greek_metrics/tests/test_example.py
orangecontrib/ancient_greek_metrics/tutorials/__init__.py
orangecontrib/ancient_greek_metrics/tutorials/metriconc_v3.4.ows
orangecontrib/ancient_greek_metrics/tutorials/spectrongram_v3.3.ows
orangecontrib/ancient_greek_metrics/widgets/__init__.py
orangecontrib/ancient_greek_metrics/widgets/ngrams.py
orangecontrib/ancient_greek_metrics/widgets/positions.py
orangecontrib/ancient_greek_metrics/widgets/positionsFR.py
orangecontrib/ancient_greek_metrics/widgets/spectrum.py
orangecontrib/ancient_greek_metrics/widgets/icons/NGram_16.png
orangecontrib/ancient_greek_metrics/widgets/icons/NGram_36.png
orangecontrib/ancient_greek_metrics/widgets/icons/NGram_48.png
orangecontrib/ancient_greek_metrics/widgets/icons/NGram_54.png
orangecontrib/ancient_greek_metrics/widgets/icons/category.svg
orangecontrib/ancient_greek_metrics/widgets/icons/lyre.png
orangecontrib/ancient_greek_metrics/widgets/icons/positions.svg
orangecontrib/ancient_greek_metrics/widgets/icons/spectrum.svg