Metadata-Version: 1.0
Name: Orange3-Ancient-Greek-Metrics
Version: 0.0.6
Summary: Add-on for analyzing Ancient Greek metrics
Home-page: UNKNOWN
Author: UNKNOWN
Author-email: UNKNOWN
License: BSD
Keywords: orange3 add-on
Platform: UNKNOWN
